incubus/__init__.py
incubus_keremkoseoglu-0.0.2.dist-info/METADATA
incubus_keremkoseoglu-0.0.2.dist-info/WHEEL
incubus_keremkoseoglu-0.0.2.dist-info/top_level.txt
incubus_keremkoseoglu-0.0.2.dist-info/RECORD
