Metadata-Version: 2.1
Name: incubus-keremkoseoglu
Version: 0.0.2
Summary: Idle app killer
Home-page: https://github.com/keremkoseoglu/incubus
Author: Kerem Koseoglu
Author-email: kerem@keremkoseoglu.com
License: UNKNOWN
Platform: UNKNOWN
Classifier: Programming Language :: Python :: 3
Classifier: License :: OSI Approved :: MIT License
Classifier: Operating System :: OS Independent
Requires-Python: >=3.6.5
